Metadata-Version: 2.4
Name: llm-tools-rag
Version: 0.1.1
Summary: A tool plugin for LLM to enable searching over embeddings
Author-email: Dan Turkel <daturkel@gmail.com>
License-Expression: MIT
Requires-Python: >=3.9
Requires-Dist: llm>=0.26
Requires-Dist: sqlite-utils>=3.38
Provides-Extra: test
Requires-Dist: pytest>=8.3.5; extra == "test"
